topsis/__init__.py
topsis/topsis.py
topsis_package/__init__.py
topsis_package/topsis.py
Topsis_Naman_101903304-1.0.2.dist-info/LICENSE
Topsis_Naman_101903304-1.0.2.dist-info/METADATA
Topsis_Naman_101903304-1.0.2.dist-info/WHEEL
Topsis_Naman_101903304-1.0.2.dist-info/top_level.txt
Topsis_Naman_101903304-1.0.2.dist-info/RECORD
