Metadata-Version: 2.1
Name: Topsis-Naman-101903304
Version: 1.0.2
Summary: A Python package implementing TOPSIS technique.
Home-page: https://github.com/NamanJain1902/Topsis-Naman-101903304
Author: Naman Jain
Author-email: 1902ben10@gmail.com
License: MIT
Platform: UNKNOWN
Classifier: License :: OSI Approved :: MIT License
Classifier: Operating System :: OS Independent
Classifier: Programming Language :: Python :: 3
Classifier: Programming Language :: Python :: 3.7
Classifier: Programming Language :: Python :: 3.8
Classifier: Programming Language :: Python :: 3.9
Classifier: Programming Language :: Python :: 3.10
Requires-Dist: pandas
